{
    "th":[
    
        {
            "vid" : 1,
            "title" : " เปิดใช้งานบัตร Digital",
            "panel_link" : "ActivateDigitalCard",
            "suggest" : true,
            "youtube_id" : "lnO-F7TzD-0",
            "thumbnail" : "https://www.ktc.co.th/pub/media/sites/ktc-digitalcard/react/img/Youtube-Cover-Activate-KTC-DIGITAL-Credit-Card.webp",
            "active" :  true
        },

        {
            "vid" : 2,
            "title" : "ดูข้อมูลบัตร",
            "panel_link" : "ViewCardInfo",
            "suggest" : true,
            "youtube_id" : "lwjpC9qajuc",
            "thumbnail" : "https://www.ktc.co.th/pub/media/sites/ktc-digitalcard/react/img/Youtube-Cover-View-Card-Info.webp",
            "active" :  true
        },
        {
            "vid" : 3,
            "title" : "ขอออกบัตรไร้หมายเลข",
            "panel_link" : "RequestNumberlessCard",
            "suggest" : true,
            "youtube_id" : "7kBQmix5Eas",
            "thumbnail" : "https://www.ktc.co.th/pub/media/sites/ktc-digitalcard/react/img/Youtube-Cover-Request-Physical-Card.webp",
            "active" :  false
        },
        {
            "vid" : 4,
            "title" : "เปิดใช้งานบัตรไร้หมายเลข",
            "panel_link" : "ActivateNumberlessCar",
            "suggest" : true,
            "youtube_id" : "02SbboZvcQQ",
            "thumbnail" : "https://www.ktc.co.th/pub/media/sites/ktc-digitalcard/react/img/Youtube-Cover-Activate-Physical-Card-MC.webp",
            "active" :  false
        }



    ],
    "en":[

        {
            "vid" : 1,
            "title" : " Activate Digital Card",
            "panel_link" : "ActivateDigitalCard",
            "suggest" : true,
            "youtube_id" : "lnO-F7TzD-0",
            "thumbnail" : "https://www.ktc.co.th/pub/media/sites/ktc-digitalcard/react/img/Youtube-Cover-Activate-KTC-DIGITAL-Credit-Card.webp",
            "active" :  true
        },
        {
            "vid" : 2,
            "title" : "View Card Info",
            "panel_link" : "ViewCardInfo",
            "suggest" : true,
            "youtube_id" : "lwjpC9qajuc",
            "thumbnail" : "https://www.ktc.co.th/pub/media/sites/ktc-digitalcard/react/img/Youtube-Cover-View-Card-Info.webp",
            "active" :  true
        },
        {
            "vid" : 3,
            "title" : "Request Numberless Card",
            "panel_link" : "RequestNumberlessCard",
            "suggest" : true,
            "youtube_id" : "7kBQmix5Eas",
            "thumbnail" : "https://www.ktc.co.th/pub/media/sites/ktc-digitalcard/react/img/Youtube-Cover-Request-Physical-Card.webp",
            "active" :  false
        },
        {
            "vid" : 4,
            "title" : "Activate Numberless Card",
            "panel_link" : "ActivateNumberlessCar",
            "suggest" : true,
            "youtube_id" : "02SbboZvcQQ",
            "thumbnail" : "https://www.ktc.co.th/pub/media/sites/ktc-digitalcard/react/img/Youtube-Cover-Activate-Physical-Card-MC.webp",
            "active" :  false
        }
    ]
}